agentfacts/__init__.py
agentfacts/core.py
agentfacts/exceptions.py
agentfacts/group.py
agentfacts/logging.py
agentfacts/models.py
agentfacts/py.typed
agentfacts/schema.py
agentfacts/utils.py
agentfacts/cli/__init__.py
agentfacts/cli/main.py
agentfacts/crypto/__init__.py
agentfacts/crypto/canonicalization.py
agentfacts/crypto/did.py
agentfacts/crypto/keys.py
agentfacts/crypto/signing.py
agentfacts/integrations/__init__.py
agentfacts/integrations/base.py
agentfacts/integrations/utils.py
agentfacts/integrations/autogen/__init__.py
agentfacts/integrations/autogen/factory.py
agentfacts/integrations/autogen/introspector.py
agentfacts/integrations/crewai/__init__.py
agentfacts/integrations/crewai/factory.py
agentfacts/integrations/crewai/introspector.py
agentfacts/integrations/huggingface/__init__.py
agentfacts/integrations/huggingface/factory.py
agentfacts/integrations/huggingface/introspector.py
agentfacts/integrations/langchain/__init__.py
agentfacts/integrations/langchain/callback.py
agentfacts/integrations/langchain/introspector.py
agentfacts/integrations/llamaindex/__init__.py
agentfacts/integrations/llamaindex/factory.py
agentfacts/integrations/llamaindex/introspector.py
agentfacts/integrations/openagents/__init__.py
agentfacts/integrations/openagents/factory.py
agentfacts/integrations/openagents/introspector.py
agentfacts/merkle/__init__.py
agentfacts/merkle/log.py
agentfacts/merkle/tree.py
agentfacts/middleware/__init__.py
agentfacts/middleware/fastapi.py
agentfacts/middleware/flask.py
agentfacts/middleware/headers.py
agentfacts/plugins/__init__.py
agentfacts/plugins/attestation.py
agentfacts/plugins/context.py
agentfacts/plugins/did.py
agentfacts/plugins/governance.py
agentfacts/plugins/metadata.py
agentfacts/plugins/registry.py
agentfacts/plugins/status.py
agentfacts/policy/__init__.py
agentfacts/policy/engine.py
agentfacts/policy/rules.py
agentfacts/testing/__init__.py
agentfacts-0.1.0.dist-info/METADATA
agentfacts-0.1.0.dist-info/WHEEL
agentfacts-0.1.0.dist-info/entry_points.txt
agentfacts-0.1.0.dist-info/licenses/LICENSE
agentfacts-0.1.0.dist-info/RECORD
