Metadata-Version: 2.4
Name: agentfacts
Version: 0.1.0
Summary: The open source SDK for AI agents Identity.
Project-URL: Homepage, https://github.com/agentfacts/agentfacts-py
Project-URL: Documentation, https://agentfacts.ai/docs
Project-URL: Repository, https://github.com/agentfacts/agentfacts-py
Author: AgentFacts Team
License-Expression: MIT
License-File: LICENSE
Keywords: agents,ai,cryptography,did,identity,langchain,llm,trust,verification
Classifier: Development Status :: 3 - Alpha
Classifier: Intended Audience :: Developers
Classifier: License :: OSI Approved :: MIT License
Classifier: Operating System :: OS Independent
Classifier: Programming Language :: Python :: 3
Classifier: Programming Language :: Python :: 3.10
Classifier: Programming Language :: Python :: 3.11
Classifier: Programming Language :: Python :: 3.12
Classifier: Programming Language :: Python :: 3.13
Classifier: Topic :: Scientific/Engineering :: Artificial Intelligence
Classifier: Topic :: Security :: Cryptography
Classifier: Topic :: Software Development :: Libraries :: Python Modules
Classifier: Typing :: Typed
Requires-Python: >=3.10
Requires-Dist: cryptography>=41.0.0
Requires-Dist: httpx>=0.25.0
Requires-Dist: pydantic>=2.0.0
Requires-Dist: pyld>=2.0.0
Provides-Extra: all
Requires-Dist: click>=8.0.0; extra == 'all'
Requires-Dist: fastapi>=0.100.0; extra == 'all'
Requires-Dist: flask>=3.0.0; extra == 'all'
Requires-Dist: rich>=13.0.0; extra == 'all'
Provides-Extra: cli
Requires-Dist: click>=8.0.0; extra == 'cli'
Requires-Dist: rich>=13.0.0; extra == 'cli'
Provides-Extra: middleware
Requires-Dist: fastapi>=0.100.0; extra == 'middleware'
Requires-Dist: flask>=3.0.0; extra == 'middleware'
